Metadata-Version: 2.1
Name: AICreator
Version: 0.1.2
Summary: AI Creator Package By - oren
Home-page: 
Author: oren
Author-email: orennadle@gmail.com
License: MIT
Keywords: ai
Classifier: Development Status :: 5 - Production/Stable
Classifier: Intended Audience :: Education
Classifier: Operating System :: Microsoft :: Windows :: Windows 10
Classifier: License :: OSI Approved :: MIT License
Classifier: Programming Language :: Python :: 3
License-File: LICENCE.txt
